Metadata-Version: 1.1
Name: illumina-utils
Version: 2.11
Summary: A library and collection of scripts to work with Illumina paired-end data (for CASAVA 1.8+).
Home-page: https://github.com/meren/illumina-utils
Author: Illumina Utils Authors
Author-email: a.murat.eren@gmail.com
License: GPLv3+
Platform: UNKNOWN
Classifier: Development Status :: 4 - Beta
Classifier: Environment :: Console
Classifier: Intended Audience :: Science/Research
Classifier: License :: OSI Approved :: GNU General Public License v3 or later (GPLv3+)
Classifier: Natural Language :: English
Classifier: Operating System :: MacOS
Classifier: Operating System :: POSIX
Classifier: Programming Language :: Python :: 3 :: Only
Classifier: Topic :: Scientific/Engineering
